schemarize/__init__.py
schemarize/core.py
schemarize/infer.py
schemarize/readers.py
schemarize/schema.py
schemarize-0.1.3.dist-info/licenses/LICENSE
schemarize-0.1.3.dist-info/METADATA
schemarize-0.1.3.dist-info/WHEEL
schemarize-0.1.3.dist-info/top_level.txt
schemarize-0.1.3.dist-info/RECORD
