Metadata-Version: 2.4
Name: schemarize
Version: 0.1.3
Summary: A toolkit to infer data schemas from samples
Author-email: Jason Frazier <jasonxfrazier@gmail.com>
License: MIT
License-File: LICENSE
Requires-Dist: ijson
Requires-Dist: pandas
Requires-Dist: pyarrow
Requires-Dist: pytest
Requires-Dist: black
Requires-Dist: isort
Requires-Dist: ruff
Requires-Dist: mypy
Requires-Dist: PyYAML
Requires-Dist: types-PyYAML
Dynamic: license-file
